blahblah/__init__.py
blahblah/_consts.py
blahblah/_generator.py
blahblah/_random.py
blahblah/_regex_generator.py
blahblah/_version.py
blahblah/py.typed
blahblah-1.8.0.dist-info/LICENSE.txt
blahblah-1.8.0.dist-info/METADATA
blahblah-1.8.0.dist-info/WHEEL
blahblah-1.8.0.dist-info/top_level.txt
blahblah-1.8.0.dist-info/RECORD
