Metadata-Version: 2.1
Name: blahblah
Version: 1.8.0
Summary: Fake data generator for district42 schema
Home-page: https://github.com/d42-schemas/blahblah
Author: Nikita Tsvetkov
Author-email: tsv1@fastmail.com
License: Apache-2.0
Project-URL: Docs, https://d42.vedro.io
Project-URL: GitHub, https://github.com/d42-schemas/blahblah
Classifier: License :: OSI Approved :: Apache Software License
Classifier: Programming Language :: Python :: 3.8
Classifier: Programming Language :: Python :: 3.9
Classifier: Programming Language :: Python :: 3.10
Classifier: Programming Language :: Python :: 3.11
Classifier: Programming Language :: Python :: 3.12
Classifier: Typing :: Typed
Requires-Python: >=3.8
License-File: LICENSE.txt
Requires-Dist: niltype <2.0,>=0.3
Requires-Dist: district42 <1.9,>=1.8.0
